fifbucket/__init__.py
fifbucket/client.py
fifbucket/fifbucket.py
fifbucket/version.py
tests/__init__.py
tests/test_functions.py
fifbucket-0.10.2.dist-info/METADATA
fifbucket-0.10.2.dist-info/WHEEL
fifbucket-0.10.2.dist-info/top_level.txt
fifbucket-0.10.2.dist-info/RECORD
