Metadata-Version: 2.1
Name: fifbucket
Version: 0.10.2
Summary: Bitbucket Api Library
Home-page: https://github.com/fiftech/fifbucket
Author: Mario Faundez
Author-email: mariofaundez@hotmail.com
License: MIT
Download-URL: https://github.com/fiftech/fifbucket/archive/0.10.2.tar.gz
Keywords: bitbucket
Platform: UNKNOWN
Requires-Dist: requests (==2.21.0)
